opticr/__init__.py
opticr/fetchdocument.py
opticr/ocr/__init__.py
opticr/ocr/baseocr.py
opticr/ocr/googlevision.py
opticr/ocr/tesseract.py
opticr/ocr/textract.py
opticr/opticr.py
opticr/utils.py
opticr-0.2.0.dist-info/LICENSE
opticr-0.2.0.dist-info/WHEEL
opticr-0.2.0.dist-info/METADATA
opticr-0.2.0.dist-info/RECORD
