Metadata-Version: 2.1
Name: opticr
Version: 0.2.0
Summary: expose a single interface and API to few OCR tools
License: Apache-2.0
Author: lzayep
Author-email: ec@lza.sh
Requires-Python: >=3.10,<4.0
Classifier: License :: OSI Approved :: Apache Software License
Classifier: Programming Language :: Python :: 3
Classifier: Programming Language :: Python :: 3.10
Requires-Dist: ocrmypdf (>=14.0.0,<15.0.0)
Requires-Dist: pdf2image (>=1.16.0,<2.0.0)
Requires-Dist: pydantic (>=1.10.2,<2.0.0)
Requires-Dist: pytesseract (>=0.3.10,<0.4.0)
Requires-Dist: requests (>=2.28.1,<3.0.0)
